simple_build_tools/__init__.py
simple_build_tools/cli.py
simple_build_tools/flake8.py
simple_build_tools/flake8.txt
simple_build_tools/gitignore.py
simple_build_tools/gitignore.txt
simple_build_tools/nexus.py
simple_build_tools/pip_config.py
simple_build_tools-1.0.4.dist-info/entry_points.txt
simple_build_tools-1.0.4.dist-info/METADATA
simple_build_tools-1.0.4.dist-info/WHEEL
simple_build_tools-1.0.4.dist-info/RECORD
