Metadata-Version: 2.1
Name: simple-build-tools
Version: 1.0.4
Summary: Build Tools for Python Projects
License: MIT
Author: James Barwick
Author-email: jbarwick@me.com
Maintainer: Ethan Chan
Maintainer-email: ethan.chan@singtel.com
Requires-Python: >=3.12,<4.0
Classifier: License :: OSI Approved :: MIT License
Classifier: Operating System :: OS Independent
Classifier: Programming Language :: Python :: 3
Classifier: Programming Language :: Python :: 3.12
